{
    "display": {
        "icon": {
            "item": "minecraft:obsidian"
        },
        "title": {"translate":"The Struggle Nether Ends"},
        "description": {"translate":"Place one of every nether block in The End"},
        "announce_to_chat": "true",
		"frame": "challenge"
    },
    "parent": "blazeandcave:nether/spreading_corruption",
	"rewards": {
		"function": "bc_rewards:nether/the_struggle_nether_ends"
    },		
    "criteria": {
        "netherrack": {
            "trigger": "minecraft:placed_block",
            "conditions": {
				"block": "minecraft:netherrack",
				"location": {
					"dimension": "the_end"
				}
            }
        },
        "soul_sand": {
            "trigger": "minecraft:placed_block",
            "conditions": {
				"block": "minecraft:soul_sand",
				"location": {
					"dimension": "the_end"
				}
            }
        },
        "glowstone": {
            "trigger": "minecraft:placed_block",
            "conditions": {
				"block": "minecraft:glowstone",
				"location": {
					"dimension": "the_end"
				}
            }
        },
        "magma_block": {
            "trigger": "minecraft:placed_block",
            "conditions": {
				"block": "minecraft:magma_block",
				"location": {
					"dimension": "the_end"
				}
            }
        },
        "soul_soil": {
            "trigger": "minecraft:placed_block",
            "conditions": {
				"block": "minecraft:soul_soil",
				"location": {
					"dimension": "the_end"
				}
            }
        },
        "basalt": {
            "trigger": "minecraft:placed_block",
            "conditions": {
				"block": "minecraft:basalt",
				"location": {
					"dimension": "the_end"
				}
            }
        },
        "ancient_debris": {
            "trigger": "minecraft:placed_block",
            "conditions": {
				"block": "minecraft:ancient_debris",
				"location": {
					"dimension": "the_end"
				}
            }
        },
        "crimson_nylium": {
            "trigger": "minecraft:placed_block",
            "conditions": {
				"block": "minecraft:crimson_nylium",
				"location": {
					"dimension": "the_end"
				}
            }
        },
        "warped_nylium": {
            "trigger": "minecraft:placed_block",
            "conditions": {
				"block": "minecraft:warped_nylium",
				"location": {
					"dimension": "the_end"
				}
            }
        },
        "crimson_stem": {
            "trigger": "minecraft:placed_block",
            "conditions": {
				"block": "minecraft:crimson_stem",
				"location": {
					"dimension": "the_end"
				}
            }
        },
        "warped_stem": {
            "trigger": "minecraft:placed_block",
            "conditions": {
				"block": "minecraft:warped_stem",
				"location": {
					"dimension": "the_end"
				}
            }
        },
        "nether_wart_block": {
            "trigger": "minecraft:placed_block",
            "conditions": {
				"block": "minecraft:nether_wart_block",
				"location": {
					"dimension": "the_end"
				}
            }
        },
        "warped_wart_block": {
            "trigger": "minecraft:placed_block",
            "conditions": {
				"block": "minecraft:warped_wart_block",
				"location": {
					"dimension": "the_end"
				}
            }
        },
        "shroomlight": {
            "trigger": "minecraft:placed_block",
            "conditions": {
				"block": "minecraft:shroomlight",
				"location": {
					"dimension": "the_end"
				}
            }
        },
        "nether_quartz_ore": {
            "trigger": "minecraft:placed_block",
            "conditions": {
				"block": "minecraft:nether_quartz_ore",
				"location": {
					"dimension": "the_end"
				}
            }
        },
        "nether_gold_ore": {
            "trigger": "minecraft:placed_block",
            "conditions": {
				"block": "minecraft:nether_gold_ore",
				"location": {
					"dimension": "the_end"
				}
            }
        },
        "soul_fire": {
            "trigger": "minecraft:placed_block",
            "conditions": {
				"block": "minecraft:soul_fire",
				"location": {
					"dimension": "the_end"
				}
            }
        },
        "blackstone": {
            "trigger": "minecraft:placed_block",
            "conditions": {
				"block": "minecraft:blackstone",
				"location": {
					"dimension": "the_end"
				}
            }
        }
    }
}