{
    "display": {
        "icon": {
            "item": "minecraft:iron_sword",
			"nbt": "{Enchantments:[{id:\"minecraft:unbreaking\",lvl:1}]}"
        },
        "title": {"translate":"Novice Enchanter"},
        "description": {"translate":"Enchant 10 items"},
        "announce_to_chat": "true"
    },
    "parent": "blazeandcave:statistics/root",
	"rewards": {
		"function": "bc_rewards:statistics/novice_enchanter"
    },		
    "criteria": {
        "trigger": {
            "trigger": "minecraft:location",
			"conditions": {
				"player":  {
					"player": {
						"stats": [
							{
								"type": "minecraft:custom",
								"stat": "minecraft:enchant_item",
								"value": {
									"min": 10
								}
							}
						]
					}
				}
			}
        }
    }
}