{
    "display": {
        "icon": {
            "item": "minecraft:gold_block"
        },
        "title": {"translate":"Olympic Gold Medallist"},
        "description": {"translate":"Swim 50km"},
        "announce_to_chat": "true",
		"frame": "challenge"
    },
    "parent": "blazeandcave:statistics/olympic_athlete",
	"rewards": {
		"function": "bc_rewards:statistics/olympic_gold_medallist"
    },		
    "criteria": {
        "trigger": {
            "trigger": "minecraft:location",
			"conditions": {
				"player":  {
					"player": {
						"stats": [
							{
								"type": "minecraft:custom",
								"stat": "minecraft:swim_one_cm",
								"value": {
									"min": 5000000
								}
							}
						]
					}
				}
			}
        }
    }
}