{
    "type": "automobility:auto_mechanic_table",
    "category": "automobility:frames",
    "sortnum": 2,
    "ingredients": [
        {"item": "minecraft:redstone"},
        {"item": "minecraft:smooth_stone"},
        {"item": "minecraft:leather"},
        {"item": "minecraft:iron_block"},
        {"tag": "minecraft:stone_crafting_materials"},
        {"item": "minecraft:iron_block"},
        {"item": "minecraft:iron_ingot"}
    ],
    "result": {
        "item": "automobility:automobile_frame",
        "component": "automobility:steel_motorcar"
    }
}